pyscript/__init__.py
pyscript/__main__.py
pyscript/_generator.py
pyscript/cli.py
pyscript/plugins/__init__.py
pyscript/plugins/create.py
pyscript/plugins/hookspecs.py
pyscript/plugins/run.py
pyscript/templates/basic.html
pyscript_cli-0.3.4.dist-info/LICENSE
pyscript_cli-0.3.4.dist-info/METADATA
pyscript_cli-0.3.4.dist-info/WHEEL
pyscript_cli-0.3.4.dist-info/entry_points.txt
pyscript_cli-0.3.4.dist-info/top_level.txt
pyscript_cli-0.3.4.dist-info/RECORD
