Metadata-Version: 2.1
Name: pyscript-cli
Version: 0.3.4
Summary: Command Line Interface for PyScript
Home-page: https://github.com/pyscript/pyscript-cli
Author: Matt Kramer, Fabio Pliger, Nicholas Tollervey, Fabio Rosado, Madhur Tandon
Author-email: mkramer@anaconda.com, fpliger@anaconda.com, ntollervey@anaconda.com, frosado@anaconda.com, mtandon@anaconda.com
License: Apache-2.0
Project-URL: Documentation, https://docs.pyscript.net
Project-URL: Examples, https://pyscript.com/@examples
Project-URL: Homepage, https://pyscript.net
Project-URL: Repository, https://github.com/pyscript/pyscript-cli
Keywords: pyscript,cli,pyodide,micropython,pyscript-cli
Classifier: Development Status :: 4 - Beta
Classifier: Environment :: Console
Classifier: Intended Audience :: Developers
Classifier: License :: OSI Approved :: Apache Software License
Classifier: Programming Language :: Python :: 3
Classifier: Programming Language :: Python :: 3.9
Classifier: Programming Language :: Python :: 3.10
Classifier: Topic :: Software Development :: Code Generators
Classifier: Topic :: Software Development :: Libraries :: Python Modules
Classifier: Topic :: Software Development :: Pre-processors
Requires-Python: >=3.9
License-File: LICENSE
Requires-Dist: Jinja2 <3.2
Requires-Dist: pluggy ==1.5.0
Requires-Dist: rich <=13.7.1
Requires-Dist: toml <0.11
Requires-Dist: typer <=0.9.0
Requires-Dist: platformdirs <4.3
Requires-Dist: requests <=2.31.0
Requires-Dist: importlib-metadata ; python_version < "3.8"
Provides-Extra: dev
Requires-Dist: coverage <7.3 ; extra == 'dev'
Requires-Dist: mypy <=1.4.1 ; extra == 'dev'
Requires-Dist: pytest <7.5 ; extra == 'dev'
Requires-Dist: types-toml <0.11 ; extra == 'dev'
Requires-Dist: types-requests ; extra == 'dev'
Provides-Extra: docs
Requires-Dist: Sphinx <5.2 ; extra == 'docs'
Requires-Dist: sphinx-autobuild <2021.4.0 ; extra == 'docs'
Requires-Dist: sphinx-autodoc-typehints <1.20 ; extra == 'docs'
Requires-Dist: myst-parser <0.19.3 ; extra == 'docs'
Requires-Dist: pydata-sphinx-theme <0.13.4 ; extra == 'docs'
